<?xml version="1.0" encoding="UTF-8"?><record_update>
    <sys_choice action="DELETE" field="u_request_type" table="x_58872_needit_needit" version="3">
        <sys_choice_set action="DELETE">
            <element>u_request_type</element>
            <name>x_58872_needit_needit</name>
            <sys_class_name/>
            <sys_created_by>admin</sys_created_by>
            <sys_created_on/>
            <sys_id>ad7789752f1b5010acc154492799b6de</sys_id>
            <sys_mod_count/>
            <sys_name>u_request_type</sys_name>
            <sys_package display_value="NeedIt" source="x_58872_needit">6ead8e780f603200cd674f8ce1050ed1</sys_package>
            <sys_policy/>
            <sys_scope display_value="NeedIt">6ead8e780f603200cd674f8ce1050ed1</sys_scope>
            <sys_update_name>sys_choice_x_58872_needit_needit_u_request_type</sys_update_name>
            <sys_updated_by>admin</sys_updated_by>
            <sys_updated_on>2020-09-21 06:26:31</sys_updated_on>
        </sys_choice_set>
        <sys_update_version action="INSERT_OR_UPDATE">
            <action>DELETE</action>
            <application/>
            <file_path/>
            <instance_id>d4f40dc2db74d0505749cac5059619f9</instance_id>
            <instance_name>dev103814</instance_name>
            <name>sys_choice_x_58872_needit_needit_u_request_type</name>
            <payload><![CDATA[<?xml version="1.0" encoding="UTF-8"?><record_update><sys_choice action="DELETE" field="u_request_type" table="x_58872_needit_needit" version="3"><sys_choice_set action="DELETE"><element>u_request_type</element><name>x_58872_needit_needit</name><sys_class_name/><sys_created_by/><sys_created_on/><sys_id/><sys_mod_count/><sys_name/><sys_package/><sys_policy/><sys_scope/><sys_update_name/><sys_updated_by/><sys_updated_on>2020-09-17 12:15:07</sys_updated_on></sys_choice_set></sys_choice></record_update>]]></payload>
            <payload_hash>1828161538</payload_hash>
            <record_name>x_58872_needit_needit.u_request_type</record_name>
            <reverted_from/>
            <source>20ac365d2f5b1010acc154492799b627</source>
            <source_table>sys_update_set</source_table>
            <state>previous</state>
            <sys_created_by>admin</sys_created_by>
            <sys_created_on>2020-09-17 12:15:07</sys_created_on>
            <sys_id>2b6749752f1b5010acc154492799b610</sys_id>
            <sys_mod_count>0</sys_mod_count>
            <sys_recorded_at>1749bfd60b20000001</sys_recorded_at>
            <sys_updated_by>admin</sys_updated_by>
            <sys_updated_on>2020-09-17 12:15:07</sys_updated_on>
            <type>Choice list</type>
            <update_guid>a3674975801b501090868932e095e110</update_guid>
            <update_guid_history>a3674975801b501090868932e095e110:1828161538,2f674975db1b50100bf4e032fcb5de0c:517487937,ab6749753c1b501051ea6c1bdac70c09:555788604,2b6749754d1b5010bfa960dac9c65a06:1869147524,af59f7e512575010b121667146a676af:1965706121</update_guid_history>
        </sys_update_version>
        <sys_metadata_delete action="INSERT_OR_UPDATE">
            <sys_audit_delete/>
            <sys_class_name>sys_metadata_delete</sys_class_name>
            <sys_created_by>admin</sys_created_by>
            <sys_created_on>2020-09-17 12:15:17</sys_created_on>
            <sys_db_object display_value="" name="sys_choice_set">sys_choice_set</sys_db_object>
            <sys_id>ad7789752f1b5010acc154492799b6de</sys_id>
            <sys_metadata>ad7789752f1b5010acc154492799b6de</sys_metadata>
            <sys_mod_count>0</sys_mod_count>
            <sys_name>u_request_type</sys_name>
            <sys_package display_value="NeedIt" source="x_58872_needit">6ead8e780f603200cd674f8ce1050ed1</sys_package>
            <sys_parent/>
            <sys_policy/>
            <sys_scope display_value="NeedIt">6ead8e780f603200cd674f8ce1050ed1</sys_scope>
            <sys_scope_delete display_value="">94872a8897db403e8ee69a431de2fca4</sys_scope_delete>
            <sys_update_name>sys_choice_x_58872_needit_needit_u_request_type</sys_update_name>
            <sys_update_version display_value="sys_choice_x_58872_needit_needit_u_request_type">2b6749752f1b5010acc154492799b610</sys_update_version>
            <sys_updated_by>admin</sys_updated_by>
            <sys_updated_on>2020-09-17 12:15:17</sys_updated_on>
        </sys_metadata_delete>
    </sys_choice>
    <sys_update_version action="INSERT_OR_UPDATE">
        <action>DELETE</action>
        <application display_value="NeedIt">6ead8e780f603200cd674f8ce1050ed1</application>
        <file_path/>
        <instance_id>d4f40dc2db74d0505749cac5059619f9</instance_id>
        <instance_name>dev103814</instance_name>
        <name>sys_choice_x_58872_needit_needit_u_request_type</name>
        <payload>&lt;?xml version="1.0" encoding="UTF-8"?&gt;&lt;record_update&gt;&lt;sys_choice action="DELETE" field="u_request_type" table="x_58872_needit_needit" version="3"&gt;&lt;sys_choice_set action="DELETE"&gt;&lt;element&gt;u_request_type&lt;/element&gt;&lt;name&gt;x_58872_needit_needit&lt;/name&gt;&lt;sys_class_name/&gt;&lt;sys_created_by&gt;admin&lt;/sys_created_by&gt;&lt;sys_created_on/&gt;&lt;sys_id&gt;ad7789752f1b5010acc154492799b6de&lt;/sys_id&gt;&lt;sys_mod_count/&gt;&lt;sys_name&gt;u_request_type&lt;/sys_name&gt;&lt;sys_package display_value="NeedIt" source="x_58872_needit"&gt;6ead8e780f603200cd674f8ce1050ed1&lt;/sys_package&gt;&lt;sys_policy/&gt;&lt;sys_scope display_value="NeedIt"&gt;6ead8e780f603200cd674f8ce1050ed1&lt;/sys_scope&gt;&lt;sys_update_name&gt;sys_choice_x_58872_needit_needit_u_request_type&lt;/sys_update_name&gt;&lt;sys_updated_by&gt;admin&lt;/sys_updated_by&gt;&lt;sys_updated_on&gt;2020-09-21 06:26:31&lt;/sys_updated_on&gt;&lt;/sys_choice_set&gt;&lt;sys_update_version action="INSERT_OR_UPDATE"&gt;&lt;action&gt;DELETE&lt;/action&gt;&lt;application/&gt;&lt;file_path/&gt;&lt;instance_id&gt;d4f40dc2db74d0505749cac5059619f9&lt;/instance_id&gt;&lt;instance_name&gt;dev103814&lt;/instance_name&gt;&lt;name&gt;sys_choice_x_58872_needit_needit_u_request_type&lt;/name&gt;&lt;payload&gt;&lt;![CDATA[&lt;?xml version="1.0" encoding="UTF-8"?&gt;&lt;record_update&gt;&lt;sys_choice action="DELETE" field="u_request_type" table="x_58872_needit_needit" version="3"&gt;&lt;sys_choice_set action="DELETE"&gt;&lt;element&gt;u_request_type&lt;/element&gt;&lt;name&gt;x_58872_needit_needit&lt;/name&gt;&lt;sys_class_name/&gt;&lt;sys_created_by/&gt;&lt;sys_created_on/&gt;&lt;sys_id/&gt;&lt;sys_mod_count/&gt;&lt;sys_name/&gt;&lt;sys_package/&gt;&lt;sys_policy/&gt;&lt;sys_scope/&gt;&lt;sys_update_name/&gt;&lt;sys_updated_by/&gt;&lt;sys_updated_on&gt;2020-09-17 12:15:07&lt;/sys_updated_on&gt;&lt;/sys_choice_set&gt;&lt;/sys_choice&gt;&lt;/record_update&gt;]]&gt;&lt;/payload&gt;&lt;payload_hash&gt;1828161538&lt;/payload_hash&gt;&lt;record_name&gt;x_58872_needit_needit.u_request_type&lt;/record_name&gt;&lt;reverted_from/&gt;&lt;source&gt;20ac365d2f5b1010acc154492799b627&lt;/source&gt;&lt;source_table&gt;sys_update_set&lt;/source_table&gt;&lt;state&gt;previous&lt;/state&gt;&lt;sys_created_by&gt;admin&lt;/sys_created_by&gt;&lt;sys_created_on&gt;2020-09-17 12:15:07&lt;/sys_created_on&gt;&lt;sys_id&gt;2b6749752f1b5010acc154492799b610&lt;/sys_id&gt;&lt;sys_mod_count&gt;0&lt;/sys_mod_count&gt;&lt;sys_recorded_at&gt;1749bfd60b20000001&lt;/sys_recorded_at&gt;&lt;sys_updated_by&gt;admin&lt;/sys_updated_by&gt;&lt;sys_updated_on&gt;2020-09-17 12:15:07&lt;/sys_updated_on&gt;&lt;type&gt;Choice list&lt;/type&gt;&lt;update_guid&gt;a3674975801b501090868932e095e110&lt;/update_guid&gt;&lt;update_guid_history&gt;a3674975801b501090868932e095e110:1828161538,2f674975db1b50100bf4e032fcb5de0c:517487937,ab6749753c1b501051ea6c1bdac70c09:555788604,2b6749754d1b5010bfa960dac9c65a06:1869147524,af59f7e512575010b121667146a676af:1965706121&lt;/update_guid_history&gt;&lt;/sys_update_version&gt;&lt;sys_metadata_delete action="INSERT_OR_UPDATE"&gt;&lt;sys_audit_delete/&gt;&lt;sys_class_name&gt;sys_metadata_delete&lt;/sys_class_name&gt;&lt;sys_created_by&gt;admin&lt;/sys_created_by&gt;&lt;sys_created_on&gt;2020-09-17 12:15:17&lt;/sys_created_on&gt;&lt;sys_db_object display_value="" name="sys_choice_set"&gt;sys_choice_set&lt;/sys_db_object&gt;&lt;sys_id&gt;ad7789752f1b5010acc154492799b6de&lt;/sys_id&gt;&lt;sys_metadata&gt;ad7789752f1b5010acc154492799b6de&lt;/sys_metadata&gt;&lt;sys_mod_count&gt;0&lt;/sys_mod_count&gt;&lt;sys_name&gt;u_request_type&lt;/sys_name&gt;&lt;sys_package display_value="NeedIt" source="x_58872_needit"&gt;6ead8e780f603200cd674f8ce1050ed1&lt;/sys_package&gt;&lt;sys_parent/&gt;&lt;sys_policy/&gt;&lt;sys_scope display_value="NeedIt"&gt;6ead8e780f603200cd674f8ce1050ed1&lt;/sys_scope&gt;&lt;sys_scope_delete display_value=""&gt;94872a8897db403e8ee69a431de2fca4&lt;/sys_scope_delete&gt;&lt;sys_update_name&gt;sys_choice_x_58872_needit_needit_u_request_type&lt;/sys_update_name&gt;&lt;sys_update_version display_value="sys_choice_x_58872_needit_needit_u_request_type"&gt;2b6749752f1b5010acc154492799b610&lt;/sys_update_version&gt;&lt;sys_updated_by&gt;admin&lt;/sys_updated_by&gt;&lt;sys_updated_on&gt;2020-09-17 12:15:17&lt;/sys_updated_on&gt;&lt;/sys_metadata_delete&gt;&lt;/sys_choice&gt;&lt;/record_update&gt;</payload>
        <payload_hash>-1903179182</payload_hash>
        <record_name>x_58872_needit_needit.u_request_type</record_name>
        <reverted_from/>
        <source>b6770d752f1b5010acc154492799b6a4</source>
        <source_table>sys_update_set</source_table>
        <state>previous</state>
        <sys_created_by>admin</sys_created_by>
        <sys_created_on>2020-09-21 06:26:31</sys_created_on>
        <sys_id>480ed8cb2f171410acc154492799b6ca</sys_id>
        <sys_mod_count>0</sys_mod_count>
        <sys_recorded_at>174af57a8ff0000001</sys_recorded_at>
        <sys_updated_by>admin</sys_updated_by>
        <sys_updated_on>2020-09-21 06:26:31</sys_updated_on>
        <type>Choice list</type>
        <update_guid>c00ed8cb111714104c7c6f156cf26dca</update_guid>
        <update_guid_history>c00ed8cb111714104c7c6f156cf26dca:-1903179182,040ed8cb9e171410cc692e6209dc59c6:-1701966180,800ed8cbe517141048992007f4a8cfc3:736548692,000ed8cbb7171410608e4b215d8c3dc0:833312879,7177c9752f1b5010848473ae6b9c449f:0,a3674975801b501090868932e095e110:1828161538,2f674975db1b50100bf4e032fcb5de0c:517487937,ab6749753c1b501051ea6c1bdac70c09:555788604,2b6749754d1b5010bfa960dac9c65a06:1869147524,af59f7e512575010b121667146a676af:1965706121</update_guid_history>
    </sys_update_version>
    <sys_metadata_delete action="INSERT_OR_UPDATE">
        <sys_audit_delete/>
        <sys_class_name>sys_metadata_delete</sys_class_name>
        <sys_created_by>admin</sys_created_by>
        <sys_created_on>2020-09-21 06:26:42</sys_created_on>
        <sys_db_object display_value="" name="sys_choice_set">sys_choice_set</sys_db_object>
        <sys_id>d60e9ccb2f171410acc154492799b637</sys_id>
        <sys_metadata>d60e9ccb2f171410acc154492799b637</sys_metadata>
        <sys_mod_count>0</sys_mod_count>
        <sys_name>u_request_type</sys_name>
        <sys_package display_value="NeedIt" source="x_58872_needit">6ead8e780f603200cd674f8ce1050ed1</sys_package>
        <sys_parent/>
        <sys_policy/>
        <sys_scope display_value="NeedIt">6ead8e780f603200cd674f8ce1050ed1</sys_scope>
        <sys_scope_delete display_value="">94872a8897db403e8ee69a431de2fca4</sys_scope_delete>
        <sys_update_name>sys_choice_x_58872_needit_needit_u_request_type</sys_update_name>
        <sys_update_version display_value="sys_choice_x_58872_needit_needit_u_request_type">480ed8cb2f171410acc154492799b6ca</sys_update_version>
        <sys_updated_by>admin</sys_updated_by>
        <sys_updated_on>2020-09-21 06:26:42</sys_updated_on>
    </sys_metadata_delete>
</record_update>
